sonusai_asr_openai_whisper/__init__.py
sonusai_asr_openai_whisper/asr_functions/__init__.py
sonusai_asr_openai_whisper/asr_functions/openai_whisper.py
sonusai_asr_openai_whisper-0.2.0.dist-info/METADATA
sonusai_asr_openai_whisper-0.2.0.dist-info/WHEEL
sonusai_asr_openai_whisper-0.2.0.dist-info/RECORD
