Metadata-Version: 2.4
Name: sonusai-asr-openai-whisper
Version: 0.2.0
Summary: OpenAI Whisper ASR tools for SonusAI
Project-URL: Homepage, https://aaware.com
Author-email: Chris Eddington <chris@aaware.com>, Jason Calderwood <jason@aaware.com>
License-Expression: GPL-3.0-only
Requires-Python: <3.12,>=3.11
Requires-Dist: openai-whisper
Requires-Dist: sonusai<2.0,>=1.1
